edgelight.py
edgelight-0.1.0.dist-info/licenses/LICENSE
edgelight-0.1.0.dist-info/METADATA
edgelight-0.1.0.dist-info/WHEEL
edgelight-0.1.0.dist-info/entry_points.txt
edgelight-0.1.0.dist-info/top_level.txt
edgelight-0.1.0.dist-info/RECORD
