Metadata-Version: 2.4
Name: edgelight
Version: 0.1.0
Summary: A PyQt6-based screen edge lighting overlay for Windows and Linux
Author-email: Your Name <your.email@example.com>
License-Expression: MIT
Project-URL: Homepage, https://github.com/yourusername/edgelight
Project-URL: Repository, https://github.com/yourusername/edgelight
Project-URL: Issues, https://github.com/yourusername/edgelight/issues
Keywords: desktop,overlay,lighting,pyqt6,gui
Classifier: Development Status :: 3 - Alpha
Classifier: Intended Audience :: End Users/Desktop
Classifier: Operating System :: Microsoft :: Windows
Classifier: Operating System :: POSIX :: Linux
Classifier: Programming Language :: Python :: 3
Classifier: Programming Language :: Python :: 3.8
Classifier: Programming Language :: Python :: 3.9
Classifier: Programming Language :: Python :: 3.10
Classifier: Programming Language :: Python :: 3.11
Classifier: Programming Language :: Python :: 3.12
Classifier: Topic :: Desktop Environment
Classifier: Topic :: Multimedia :: Graphics
Requires-Python: >=3.8
License-File: LICENSE
Requires-Dist: PyQt6>=6.0.0
Dynamic: license-file
